[
    {
        "id": 1,
        "name": "Chocolate Truffle Cake",
        "price": "$25",
        "image": "assets/images/chocolate_truffle.jpg",
        "description": "Rich and creamy chocolate truffle cake for any occasion."
    },
    {
        "id": 2,
        "name": "Strawberry Cheesecake",
        "price": "$30",
        "image": "assets/images/strawberry_cheesecake.jpg",
        "description": "Delicious strawberry cheesecake with a crispy base."
    },
    {
        "id": 3,
        "name": "Classic Red Velvet",
        "price": "$28",
        "image": "assets/images/red_velvet.jpg",
        "description": "A smooth, classic red velvet cake with cream cheese frosting."
    }
]
